LICENSE.txt
README.md
setup.cfg
setup.py
nwsapy/__init__.py
nwsapy/entrypoint.py
nwsapy.egg-info/PKG-INFO
nwsapy.egg-info/SOURCES.txt
nwsapy.egg-info/dependency_links.txt
nwsapy.egg-info/requires.txt
nwsapy.egg-info/top_level.txt
nwsapy/core/__init__.py
nwsapy/core/errors.py
nwsapy/core/geometry.py
nwsapy/core/mapping.py
nwsapy/core/inheritance/__init__.py
nwsapy/core/inheritance/base_endpoint.py
nwsapy/core/inheritance/iterator.py
nwsapy/core/inheritance/request_error.py
nwsapy/endpoints/__init__.py
nwsapy/endpoints/alerts.py
nwsapy/endpoints/glossary.py
nwsapy/endpoints/point.py
nwsapy/endpoints/server_ping.py
nwsapy/endpoints/template.py
nwsapy/services/__init__.py
nwsapy/services/request.py
nwsapy/services/set_data.py
nwsapy/services/url_constructor.py
nwsapy/services/validation.py
old_package/__init__.py
old_package/alerts.py
old_package/errors.py
old_package/geometry.py
old_package/glossary.py
old_package/gridpoints.py
old_package/nwsapy.py
old_package/points.py
old_package/stub.py
old_package/url_constructor.py
old_package/utils.py
old_package/geometry/__init__.py
old_package/geometry/shapes.py
old_package/tests/__init__.py
old_package/tests/package_test.py
old_package/tests/tests.py
old_package/tests/alerts/__init__.py
old_package/tests/alerts/alertbyid.py
old_package/tests/alerts/individual_alerts.py
old_package/tests/points/__init__.py
old_package/tests/points/test_point.py
old_package/tests/urlconstructor/__init__.py
old_package/tests/urlconstructor/test_url_constructor.py