Metadata-Version: 2.1
Name: nwsapy
Version: 1.0.1
Summary: A pythonic implementation of the National Weather Service API
Home-page: https://github.com/WxBDM/nwsapy
Author: Brandon Molyneaux
License: apache-2.0
Download-URL: https://github.com/WxBDM/nwsapy/archive/refs/tags/v1.0.1.tar.gz
Keywords: national weather service,nws,nws api
Platform: UNKNOWN
Classifier: Development Status :: 3 - Alpha
Classifier: Intended Audience :: Developers
Classifier: Topic :: Software Development :: Build Tools
Classifier: License :: OSI Approved :: Apache Software License
Classifier: Programming Language :: Python :: 3
Classifier: Programming Language :: Python :: 3.8
Classifier: Programming Language :: Python :: 3.9
Requires-Python: >=3.8
